metadataschemas/document_schema.py
metadataschemas/geospatial_schema.py
metadataschemas/image_schema.py
metadataschemas/indicator_schema.py
metadataschemas/indicators_db_schema.py
metadataschemas/metadata_manager.py
metadataschemas/microdata_schema.py
metadataschemas/resource_schema.py
metadataschemas/script_schema.py
metadataschemas/table_schema.py
metadataschemas/utils/__init__.py
metadataschemas/utils/enum_with_value_or_key.py
metadataschemas/utils/excel_to_pydantic.py
metadataschemas/utils/pydantic_to_excel.py
metadataschemas/utils/quick_start.py
metadataschemas/utils/schema_base_model.py
metadataschemas/utils/test_utils.py
metadataschemas/utils/utils.py
metadataschemas/video_schema.py
metadataschemas-0.1.3.dist-info/LICENSE
metadataschemas-0.1.3.dist-info/METADATA
metadataschemas-0.1.3.dist-info/WHEEL
metadataschemas-0.1.3.dist-info/RECORD
