Metadata-Version: 2.1
Name: metadataschemas
Version: 0.1.3
Summary: A library of metadata schemas for documents, geospatial, image, indicator (timeseries), microdata (ddi), script, table and video data
License: MIT
Author: Mehmood Asghar
Author-email: masghar@worldbank.org
Requires-Python: >=3.11,<4.0
Classifier: License :: OSI Approved :: MIT License
Classifier: Programming Language :: Python :: 3
Classifier: Programming Language :: Python :: 3.11
Classifier: Programming Language :: Python :: 3.12
Requires-Dist: certifi (>=2024.8.30,<2025.0.0)
Requires-Dist: numpy (>=2.1.0,<3.0.0)
Requires-Dist: openpyxl (>=3.1.5,<4.0.0)
Requires-Dist: pandas (>=2.2.2,<3.0.0)
Requires-Dist: pydantic (>=2.8.0,<3.0.0)
Requires-Dist: rich (>=13.9.4,<14.0.0)
